sparse_dot_mkl/__init__.py
sparse_dot_mkl/_dense_dense.py
sparse_dot_mkl/_gram_matrix.py
sparse_dot_mkl/_sparse_dense.py
sparse_dot_mkl/_sparse_qr_solver.py
sparse_dot_mkl/_sparse_sparse.py
sparse_dot_mkl/_sparse_sypr.py
sparse_dot_mkl/_sparse_vector.py
sparse_dot_mkl/sparse_array.py
sparse_dot_mkl/sparse_dot.py
sparse_dot_mkl/_mkl_interface/__init__.py
sparse_dot_mkl/_mkl_interface/_cfunctions.py
sparse_dot_mkl/_mkl_interface/_common.py
sparse_dot_mkl/_mkl_interface/_constants.py
sparse_dot_mkl/_mkl_interface/_load_library.py
sparse_dot_mkl/_mkl_interface/_structs.py
sparse_dot_mkl/solvers/__init__.py
sparse_dot_mkl/solvers/_cg.py
sparse_dot_mkl/solvers/_fgmres.py
sparse_dot_mkl/solvers/_iss.py
sparse_dot_mkl/solvers/_pardiso.py
sparse_dot_mkl/tests/__init__.py
sparse_dot_mkl/tests/test_dense_dense.py
sparse_dot_mkl/tests/test_gram_matrix.py
sparse_dot_mkl/tests/test_iss.py
sparse_dot_mkl/tests/test_mkl.py
sparse_dot_mkl/tests/test_pardiso.py
sparse_dot_mkl/tests/test_qr_solver.py
sparse_dot_mkl/tests/test_scipy_classes.py
sparse_dot_mkl/tests/test_service.py
sparse_dot_mkl/tests/test_sparse_dense.py
sparse_dot_mkl/tests/test_sparse_sparse.py
sparse_dot_mkl/tests/test_sparse_vector.py
sparse_dot_mkl-0.9.10.dist-info/licenses/LICENSE
sparse_dot_mkl-0.9.10.dist-info/METADATA
sparse_dot_mkl-0.9.10.dist-info/WHEEL
sparse_dot_mkl-0.9.10.dist-info/top_level.txt
sparse_dot_mkl-0.9.10.dist-info/zip-safe
sparse_dot_mkl-0.9.10.dist-info/RECORD
