Metadata-Version: 2.4
Name: sparse_dot_mkl
Version: 0.9.10
Summary: Intel MKL wrapper for sparse matrix multiplication
Home-page: https://github.com/flatironinstitute/sparse_dot
Author: Chris Jackson
Author-email: cj59@nyu.edu
License: MIT
Classifier: Programming Language :: Python :: 3
Classifier: License :: OSI Approved :: MIT License
Classifier: Operating System :: OS Independent
Classifier: Development Status :: 4 - Beta
License-File: LICENSE
Requires-Dist: numpy
Requires-Dist: scipy
Dynamic: author
Dynamic: author-email
Dynamic: classifier
Dynamic: description
Dynamic: description-content-type
Dynamic: home-page
Dynamic: license
Dynamic: license-file
Dynamic: requires-dist
Dynamic: summary
